tweepyauth/__init__.py
tweepyauth/greet.py
tweepyauth/tweepyAuth.py
tweepyauth-1.1.1.dist-info/LICENSE.txt
tweepyauth-1.1.1.dist-info/METADATA
tweepyauth-1.1.1.dist-info/WHEEL
tweepyauth-1.1.1.dist-info/top_level.txt
tweepyauth-1.1.1.dist-info/RECORD
