Metadata-Version: 2.1
Name: tweepyauth
Version: 1.1.1
Summary: A small library to ease tweepy authentication
Home-page: https://gitlab.com/mocchapi/tweepyauth
Author: mocchapi
Author-email: mocchapi@gmail.com
License: UNKNOWN
Platform: UNKNOWN
Classifier: Programming Language :: Python :: 3
Classifier: License :: OSI Approved :: MIT License
Classifier: Operating System :: OS Independent
Requires-Python: >=3.6
Requires-Dist: tweepy
